modely/__init__.py
modely/commands/__init__.py
modely/commands/init_config.py
modely-0.1.3.dist-info/METADATA
modely-0.1.3.dist-info/WHEEL
modely-0.1.3.dist-info/entry_points.txt
modely-0.1.3.dist-info/RECORD
