Metadata-Version: 2.3
Name: modely
Version: 0.1.3
Summary: Add your description here
Project-URL: Homepage, https://github.com/IsaiasGutierrezCruz/modely
Author: Isaías Gutiérrez
Classifier: License :: OSI Approved :: MIT License
Classifier: Operating System :: OS Independent
Classifier: Programming Language :: Python :: 3
Requires-Python: >=3.10
Requires-Dist: click>=8.1.7
Requires-Dist: pyyaml>=6.0.2
